seekbaseapi/__init__.py
seekbaseapi/client.py
seekbaseapi-0.6.2.dist-info/licenses/LICENSE
seekbaseapi-0.6.2.dist-info/METADATA
seekbaseapi-0.6.2.dist-info/WHEEL
seekbaseapi-0.6.2.dist-info/top_level.txt
seekbaseapi-0.6.2.dist-info/RECORD
