Metadata-Version: 2.4
Name: seekbaseapi
Version: 0.6.2
Summary: A Python package for interacting with SeekBaseApi and extracting specific information.
Author: E2H
License: MIT
Classifier: Programming Language :: Python :: 3
Classifier: License :: OSI Approved :: MIT License
Classifier: Programming Language :: Python :: 3.7
Classifier: Programming Language :: Python :: 3.8
Classifier: Programming Language :: Python :: 3.9
Classifier: Programming Language :: Python :: 3.10
Classifier: Programming Language :: Python :: 3.11
Classifier: Programming Language :: Python :: 3.12
License-File: LICENSE
Requires-Dist: elasticsearch
Requires-Dist: regex
Requires-Dist: urllib3
Requires-Dist: tenacity
Requires-Dist: pydantic
Requires-Dist: pydantic[email]
Dynamic: author
Dynamic: classifier
Dynamic: description
Dynamic: description-content-type
Dynamic: license
Dynamic: license-file
Dynamic: requires-dist
Dynamic: summary
